video_scene_detect/SceneDetect.py
video_scene_detect/__init__.py
video_scene_detect/estimate_scenes_count.py
video_scene_detect/evaluation.py
video_scene_detect/h_add.py
video_scene_detect/h_nrm.py
video_scene_detect/video_multiprocess.py
video_scene_detect-0.2.dist-info/METADATA
video_scene_detect-0.2.dist-info/WHEEL
video_scene_detect-0.2.dist-info/top_level.txt
video_scene_detect-0.2.dist-info/RECORD
