Metadata-Version: 2.1
Name: video-scene-detect
Version: 0.2
Summary: Scene detection from video files(.mp4)
Author: Chandan Verma
Author-email: verma.chandan01@gmail.com
